razaltlib/__init__.py
razaltlib/dir/__init__.py
razaltlib/dir/compare.py
razaltlib-0.1.4.dist-info/METADATA
razaltlib-0.1.4.dist-info/WHEEL
razaltlib-0.1.4.dist-info/RECORD
